LICENSE
README.md
setup.py
geoview/__init__.py
geoview/__main__.py
geoview/utils.py
geoview.egg-info/PKG-INFO
geoview.egg-info/SOURCES.txt
geoview.egg-info/dependency_links.txt
geoview.egg-info/not-zip-safe
geoview.egg-info/requires.txt
geoview.egg-info/top_level.txt
geoview/cli/__init__.py
geoview/cli/__main__.py